beaupy/__init__.py
beaupy/_beaupy.py
beaupy/_internals.py
beaupy/spinners/__init__.py
beaupy/spinners/_spinners.py
beaupy-3.11.0.dist-info/METADATA
beaupy-3.11.0.dist-info/WHEEL
beaupy-3.11.0.dist-info/licenses/LICENSE
beaupy-3.11.0.dist-info/RECORD
