Metadata-Version: 2.4
Name: beaupy
Version: 3.11.0
Summary: A library of elements for interactive TUIs in Python
License: MIT
License-File: LICENSE
Keywords: cli,interactive,console,terminal,interface
Author: Peter Vyboch
Author-email: pvyboch1@gmail.com
Requires-Python: >=3.7.8,<4.0.0
Classifier: Development Status :: 5 - Production/Stable
Classifier: Environment :: Console
Classifier: Intended Audience :: Developers
Classifier: License :: OSI Approved :: MIT License
Classifier: Programming Language :: Python :: 3
Classifier: Programming Language :: Python :: 3.8
Classifier: Programming Language :: Python :: 3.9
Classifier: Programming Language :: Python :: 3.10
Classifier: Programming Language :: Python :: 3.11
Classifier: Programming Language :: Python :: 3.12
Classifier: Programming Language :: Python :: 3.13
Classifier: Programming Language :: Python :: 3.14
Classifier: Topic :: Terminals
Requires-Dist: emoji (>=2.0.0,<3.0.0)
Requires-Dist: python-yakh (>=0.4.1,<0.5.0)
Requires-Dist: questo (>=0.4.1,<0.5.0)
Requires-Dist: rich (>=12.2.0)
Project-URL: Repository, https://github.com/petereon/beaupy
